composable_dataloader/__init__.py
composable_dataloader/base_data_loader.py
composable_dataloader/databricks.py
composable_dataloader/dynamic_cli_mixin.py
composable_dataloader/engine.py
composable_dataloader/format.py
composable_dataloader/logger.py
composable_dataloader/output.py
composable_dataloader/py.typed
composable_dataloader-10.0.7.dist-info/METADATA
composable_dataloader-10.0.7.dist-info/WHEEL
composable_dataloader-10.0.7.dist-info/RECORD
